driftfx/__init__.py
driftfx/__main__.py
driftfx/core.py
driftfx/_cython/__init__.py
driftfx/_cython/levenshtein.c
driftfx/_cython/levenshtein.cpython-39-darwin.so
driftfx-0.1.1.dist-info/licenses/LICENSE
driftfx-0.1.1.dist-info/METADATA
driftfx-0.1.1.dist-info/WHEEL
driftfx-0.1.1.dist-info/entry_points.txt
driftfx-0.1.1.dist-info/top_level.txt
driftfx-0.1.1.dist-info/RECORD
