Metadata-Version: 2.4
Name: driftfx
Version: 0.1.1
Summary: Zero-false-positive data drift detection with Cython-optimized performance
Home-page: https://github.com/qckfx/driftfx
Author: Chris Wood
Author-email: Chris Wood <chris.wood@qckfx.com>
License: MIT
Project-URL: Homepage, https://github.com/qckfx/driftfx
Project-URL: Changelog, https://github.com/qckfx/driftfx/releases
Requires-Python: >=3.9
License-File: LICENSE
Requires-Dist: pandas>=2.0
Dynamic: author
Dynamic: home-page
Dynamic: license-file
Dynamic: requires-python
